prosessor/pc.v
module pc(CLK, RST, D, Q);
    input CLK, RST;
    input[31:0] D;

    output[31:0] Q;
    reg[31:0]    Q;

    always @ (posedge CLK or posedge RST) begin
        if(RST == 1'b1)
            Q <= 32'h00000000;
        else
            Q <= D;
    end
endmodule

pc/tb_pc.v
`timescale 1ns/1ns

module tb_pc();
    reg CLK, RST;
    reg[31:0] D;

    wire[31:0] Q;

    parameter RATE = 100;

    pc pc(
        .CLK(CLK),
        .RST(RST),
        .D(D),
        .Q(Q)
    );

    always #(RATE/2) CLK = ~CLK;

    initial begin
        $dumpfile("tb_pc.vcd");
        $dumpvars(0, pc);
        $monitor($stime, " CLK = %d, RST = %d, D = %x, Q = %x", CLK, RST, D, pc.Q);
    end

    initial begin
        #0      CLK = 0;
                RST = 0;
                D   = 32'h00000000;

        #(RATE) D = 32'h00000004;
        #(RATE) D = 32'h00000008;
        #(RATE) D = 32'h0000000C;
        #(RATE) D = 32'h00000400;
        #(RATE) D = 32'h00000200;
                RST = 1;
        #10     D = 32'h00000004;
                RST = 0;
        #(RATE - 10) D = 32'h00000008;
        #(RATE) $finish;
    end
    
endmodule

pc/tb_pc.vcd
$date
	Wed Sep 04 05:59:02 2024
$end
$version
	Icarus Verilog
$end
$timescale
	1ns
$end
$scope module tb_pc $end
$scope module pc $end
$var wire 1 ! CLK $end
$var wire 32 " D [31:0] $end
$var wire 1 # RST $end
$var reg 32 $ Q [31:0] $end
$upscope $end
$upscope $end
$enddefinitions $end
$comment Show the parameter values. $end
$dumpall
$end
#0
$dumpvars
bx $
0#
b0 "
0!
$end
#50
b0 $
1!
#100
0!
b100 "
#150
b100 $
1!
#200
0!
b1000 "
#250
b1000 $
1!
#300
0!
b1100 "
#350
b1100 $
1!
#400
0!
b10000000000 "
#450
b10000000000 $
1!
#500
b0 $
0!
1#
b1000000000 "
#510
0#
b100 "
#550
b100 $
1!
#600
0!
b1000 "
#650
b1000 $
1!
